serial_scanner/__init__.py
serial_scanner/scanner.py
serial_scanner-0.1.3.dist-info/LICENSE.txt
serial_scanner-0.1.3.dist-info/METADATA
serial_scanner-0.1.3.dist-info/WHEEL
serial_scanner-0.1.3.dist-info/top_level.txt
serial_scanner-0.1.3.dist-info/RECORD
