Metadata-Version: 2.1
Name: serial_scanner
Version: 0.1.3
Summary: Serial port device scanner
Author-email: jttaufa <jonathon.taufatofua@uqconnect.edu.au>
Project-URL: Homepage, https://github.com/jttaufa/serialport_scanner
Classifier: Development Status :: 3 - Alpha
Classifier: Programming Language :: Python :: 3
Classifier: License :: OSI Approved :: GNU General Public License v3 (GPLv3)
Classifier: Operating System :: OS Independent
Requires-Python: >=3.8
License-File: LICENSE.txt
Requires-Dist: pyserial
